gsa_framework/__init__.py
gsa_framework/convergence.py
gsa_framework/model_base.py
gsa_framework/plotting.py
gsa_framework/setups_paper_gwp.py
gsa_framework/stability_convergence_metrics.py
gsa_framework/utils.py
gsa_framework/utils_paper_plotting.py
gsa_framework/utils_setac_lca.py
gsa_framework/validation.py
gsa_framework/version.py
gsa_framework/sampling/__init__.py
gsa_framework/sampling/directions.py
gsa_framework/sampling/get_samples.py
gsa_framework/sampling/sobol_sequence.py
gsa_framework/sampling/data/directions.npy
gsa_framework/sensitivity_analysis/__init__.py
gsa_framework/sensitivity_analysis/correlations.py
gsa_framework/sensitivity_analysis/delta_moment.py
gsa_framework/sensitivity_analysis/extended_FAST.py
gsa_framework/sensitivity_analysis/gradient_boosting.py
gsa_framework/sensitivity_analysis/regression_LASSO.py
gsa_framework/sensitivity_analysis/saltelli_sobol.py
gsa_framework-0.1.dist-info/LICENSE
gsa_framework-0.1.dist-info/METADATA
gsa_framework-0.1.dist-info/WHEEL
gsa_framework-0.1.dist-info/top_level.txt
gsa_framework-0.1.dist-info/RECORD
