Metadata-Version: 2.1
Name: gsa-framework
Version: 0.1
Summary: Generic framework for global sensitivity analysis
Home-page: https://github.com/aleksandra-kim/gsa_framework
Author: Aleksanda Kim
Author-email: aleksandra.kim@icloud.com
License: BSD-3-Clause
Platform: UNKNOWN
Classifier: Intended Audience :: End Users/Desktop
Classifier: Intended Audience :: Developers
Classifier: Intended Audience :: Science/Research
Classifier: License :: OSI Approved :: BSD License
Classifier: Operating System :: MacOS :: MacOS X
Classifier: Operating System :: Microsoft :: Windows
Classifier: Operating System :: POSIX
Classifier: Programming Language :: Python
Classifier: Programming Language :: Python :: 3
Classifier: Programming Language :: Python :: 3.6
Classifier: Programming Language :: Python :: 3.7
Classifier: Topic :: Scientific/Engineering :: Information Analysis
Classifier: Topic :: Scientific/Engineering :: Mathematics
Classifier: Topic :: Scientific/Engineering :: Visualization
Requires-Dist: h5py
Requires-Dist: numpy
Requires-Dist: plotly
Requires-Dist: scikit-learn
Requires-Dist: scipy
Requires-Dist: xgboost
